{
  "chart_type": "D8",
  "divisional_factor": 8,
  "chart_name": "Ashtamsa Chart",
  "signification": "Longevity, Obstacles",
  "planets": [
    {
      "id": "L",
      "name": "Ascendant",
      "short_name": "Asc",
      "house": 1,
      "house_name": "‚ôČÔłéTaurus",
      "longitude": 4.708149079103123,
      "longitude_dms": "4¬į 42‚Äô 29\""
    },
    {
      "id": 0,
      "name": "Sun‚ėČ",
      "short_name": "Su‚ėČ",
      "house": 7,
      "house_name": "‚ôŹÔłéScorpio",
      "longitude": 21.42827245879971,
      "longitude_dms": "21¬į 25‚Äô 42\""
    },
    {
      "id": 1,
      "name": "Moon‚ėĺ",
      "short_name": "Mo‚ėĺ",
      "house": 5,
      "house_name": "‚ôćÔłéVirgo",
      "longitude": 9.686263158269185,
      "longitude_dms": "9¬į 41‚Äô 11\""
    },
    {
      "id": 2,
      "name": "Mars‚ôā",
      "short_name": "Ma‚ôā",
      "house": 10,
      "house_name": "‚ôíÔłéAquarius",
      "longitude": 18.67120537665346,
      "longitude_dms": "18¬į 40‚Äô 16\""
    },
    {
      "id": 3,
      "name": "Mercury‚ėŅ",
      "short_name": "Me‚ėŅ",
      "house": 9,
      "house_name": "‚ôĎÔłéCapricorn",
      "longitude": 27.71804445198586,
      "longitude_dms": "27¬į 43‚Äô 5\""
    },
    {
      "id": 4,
      "name": "Jupiter‚ôÉ",
      "short_name": "Ju‚ôÉ",
      "house": 11,
      "house_name": "‚ôďÔłéPisces",
      "longitude": 1.0943240269557464,
      "longitude_dms": "1¬į 5‚Äô 40\""
    },
    {
      "id": 5,
      "name": "Venus‚ôÄ",
      "short_name": "Ve‚ôÄ",
      "house": 7,
      "house_name": "‚ôŹÔłéScorpio",
      "longitude": 14.995617786727735,
      "longitude_dms": "14¬į 59‚Äô 44\""
    },
    {
      "id": 6,
      "name": "Saturn‚ôĄ",
      "short_name": "Sa‚ôĄ",
      "house": 0,
      "house_name": "‚ôąAries",
      "longitude": 0.48991079499910484,
      "longitude_dms": "0¬į 29‚Äô 24\""
    },
    {
      "id": 7,
      "name": "Raagu‚ėä",
      "short_name": "Ra‚ėä",
      "house": 5,
      "house_name": "‚ôćÔłéVirgo",
      "longitude": 16.767375441145987,
      "longitude_dms": "16¬į 46‚Äô 3\""
    },
    {
      "id": 8,
      "name": "Kethu‚ėč",
      "short_name": "Ke‚ėč",
      "house": 5,
      "house_name": "‚ôćÔłéVirgo",
      "longitude": 16.767375441146214,
      "longitude_dms": "16¬į 46‚Äô 3\""
    },
    {
      "id": 9,
      "name": "Uranus‚õĘ",
      "short_name": "Ur‚õĘ",
      "house": 0,
      "house_name": "‚ôąAries",
      "longitude": 21.016806054212793,
      "longitude_dms": "21¬į 1‚Äô 1\""
    },
    {
      "id": 10,
      "name": "Neptune‚ôÜ",
      "short_name": "Ne‚ôÜ",
      "house": 11,
      "house_name": "‚ôďÔłéPisces",
      "longitude": 28.33370730478964,
      "longitude_dms": "28¬į 20‚Äô 1\""
    },
    {
      "id": 11,
      "name": "Pluto‚ôá",
      "short_name": "Pl‚ôá",
      "house": 9,
      "house_name": "‚ôĎÔłéCapricorn",
      "longitude": 24.078994525001008,
      "longitude_dms": "24¬į 4‚Äô 44\""
    }
  ],
  "houses": {
    "0": [
      {
        "id": 6,
        "name": "Saturn‚ôĄ",
        "short_name": "Sa‚ôĄ",
        "house": 0,
        "house_name": "‚ôąAries",
        "longitude": 0.48991079499910484,
        "longitude_dms": "0¬į 29‚Äô 24\""
      },
      {
        "id": 9,
        "name": "Uranus‚õĘ",
        "short_name": "Ur‚õĘ",
        "house": 0,
        "house_name": "‚ôąAries",
        "longitude": 21.016806054212793,
        "longitude_dms": "21¬į 1‚Äô 1\""
      }
    ],
    "1": [
      {
        "id": "L",
        "name": "Ascendant",
        "short_name": "Asc",
        "house": 1,
        "house_name": "‚ôČÔłéTaurus",
        "longitude": 4.708149079103123,
        "longitude_dms": "4¬į 42‚Äô 29\""
      }
    ],
    "2": [],
    "3": [],
    "4": [],
    "5": [
      {
        "id": 1,
        "name": "Moon‚ėĺ",
        "short_name": "Mo‚ėĺ",
        "house": 5,
        "house_name": "‚ôćÔłéVirgo",
        "longitude": 9.686263158269185,
        "longitude_dms": "9¬į 41‚Äô 11\""
      },
      {
        "id": 7,
        "name": "Raagu‚ėä",
        "short_name": "Ra‚ėä",
        "house": 5,
        "house_name": "‚ôćÔłéVirgo",
        "longitude": 16.767375441145987,
        "longitude_dms": "16¬į 46‚Äô 3\""
      },
      {
        "id": 8,
        "name": "Kethu‚ėč",
        "short_name": "Ke‚ėč",
        "house": 5,
        "house_name": "‚ôćÔłéVirgo",
        "longitude": 16.767375441146214,
        "longitude_dms": "16¬į 46‚Äô 3\""
      }
    ],
    "6": [],
    "7": [
      {
        "id": 0,
        "name": "Sun‚ėČ",
        "short_name": "Su‚ėČ",
        "house": 7,
        "house_name": "‚ôŹÔłéScorpio",
        "longitude": 21.42827245879971,
        "longitude_dms": "21¬į 25‚Äô 42\""
      },
      {
        "id": 5,
        "name": "Venus‚ôÄ",
        "short_name": "Ve‚ôÄ",
        "house": 7,
        "house_name": "‚ôŹÔłéScorpio",
        "longitude": 14.995617786727735,
        "longitude_dms": "14¬į 59‚Äô 44\""
      }
    ],
    "8": [],
    "9": [
      {
        "id": 3,
        "name": "Mercury‚ėŅ",
        "short_name": "Me‚ėŅ",
        "house": 9,
        "house_name": "‚ôĎÔłéCapricorn",
        "longitude": 27.71804445198586,
        "longitude_dms": "27¬į 43‚Äô 5\""
      },
      {
        "id": 11,
        "name": "Pluto‚ôá",
        "short_name": "Pl‚ôá",
        "house": 9,
        "house_name": "‚ôĎÔłéCapricorn",
        "longitude": 24.078994525001008,
        "longitude_dms": "24¬į 4‚Äô 44\""
      }
    ],
    "10": [
      {
        "id": 2,
        "name": "Mars‚ôā",
        "short_name": "Ma‚ôā",
        "house": 10,
        "house_name": "‚ôíÔłéAquarius",
        "longitude": 18.67120537665346,
        "longitude_dms": "18¬į 40‚Äô 16\""
      }
    ],
    "11": [
      {
        "id": 4,
        "name": "Jupiter‚ôÉ",
        "short_name": "Ju‚ôÉ",
        "house": 11,
        "house_name": "‚ôďÔłéPisces",
        "longitude": 1.0943240269557464,
        "longitude_dms": "1¬į 5‚Äô 40\""
      },
      {
        "id": 10,
        "name": "Neptune‚ôÜ",
        "short_name": "Ne‚ôÜ",
        "house": 11,
        "house_name": "‚ôďÔłéPisces",
        "longitude": 28.33370730478964,
        "longitude_dms": "28¬į 20‚Äô 1\""
      }
    ]
  },
  "ascendant": {
    "house": 1,
    "house_name": "‚ôČÔłéTaurus",
    "longitude": 4.708149079103123,
    "longitude_dms": "4¬į 42‚Äô 29\""
  },
  "birth_data": {
    "name": "Jai Krishna Mishra",
    "place": "allahabad",
    "date": "1994-12-28",
    "time": "18:50:00"
  }
}