{
  "chart_type": "D8",
  "divisional_factor": 8,
  "chart_name": "Ashtamsa Chart",
  "signification": "Longevity, Obstacles",
  "planets": [
    {
      "id": "L",
      "name": "Ascendant",
      "short_name": "Asc",
      "house": 2,
      "house_name": "‚ôäÔłéGemini",
      "longitude": 9.406798488562117,
      "longitude_dms": "9¬į 24‚Äô 24\""
    },
    {
      "id": 0,
      "name": "Sun‚ėČ",
      "short_name": "Su‚ėČ",
      "house": 5,
      "house_name": "‚ôćÔłéVirgo",
      "longitude": 5.92230594716375,
      "longitude_dms": "5¬į 55‚Äô 20\""
    },
    {
      "id": 1,
      "name": "Moon‚ėĺ",
      "short_name": "Mo‚ėĺ",
      "house": 3,
      "house_name": "‚ôčÔłéCancer",
      "longitude": 1.3397530748991358,
      "longitude_dms": "1¬į 20‚Äô 23\""
    },
    {
      "id": 2,
      "name": "Mars‚ôā",
      "short_name": "Ma‚ôā",
      "house": 3,
      "house_name": "‚ôčÔłéCancer",
      "longitude": 18.424194198893474,
      "longitude_dms": "18¬į 25‚Äô 27\""
    },
    {
      "id": 3,
      "name": "Mercury‚ėŅ",
      "short_name": "Me‚ėŅ",
      "house": 3,
      "house_name": "‚ôčÔłéCancer",
      "longitude": 29.358620782087428,
      "longitude_dms": "29¬į 21‚Äô 31\""
    },
    {
      "id": 4,
      "name": "Jupiter‚ôÉ",
      "short_name": "Ju‚ôÉ",
      "house": 8,
      "house_name": "‚ôźÔłéSagittarius",
      "longitude": 4.490410215297061,
      "longitude_dms": "4¬į 29‚Äô 25\""
    },
    {
      "id": 5,
      "name": "Venus‚ôÄ",
      "short_name": "Ve‚ôÄ",
      "house": 5,
      "house_name": "‚ôćÔłéVirgo",
      "longitude": 18.811939700024027,
      "longitude_dms": "18¬į 48‚Äô 43\""
    },
    {
      "id": 6,
      "name": "Saturn‚ôĄ",
      "short_name": "Sa‚ôĄ",
      "house": 7,
      "house_name": "‚ôŹÔłéScorpio",
      "longitude": 4.603429656026037,
      "longitude_dms": "4¬į 36‚Äô 12\""
    },
    {
      "id": 7,
      "name": "Raagu‚ėä",
      "short_name": "Ra‚ėä",
      "house": 8,
      "house_name": "‚ôźÔłéSagittarius",
      "longitude": 2.943214876112961,
      "longitude_dms": "2¬į 56‚Äô 36\""
    },
    {
      "id": 8,
      "name": "Kethu‚ėč",
      "short_name": "Ke‚ėč",
      "house": 8,
      "house_name": "‚ôźÔłéSagittarius",
      "longitude": 2.943214876112961,
      "longitude_dms": "2¬į 56‚Äô 36\""
    },
    {
      "id": 9,
      "name": "Uranus‚õĘ",
      "short_name": "Ur‚õĘ",
      "house": 2,
      "house_name": "‚ôäÔłéGemini",
      "longitude": 5.043360729221149,
      "longitude_dms": "5¬į 2‚Äô 36\""
    },
    {
      "id": 10,
      "name": "Neptune‚ôÜ",
      "short_name": "Ne‚ôÜ",
      "house": 0,
      "house_name": "‚ôąAries",
      "longitude": 18.999035645060758,
      "longitude_dms": "18¬į 59‚Äô 57\""
    },
    {
      "id": 11,
      "name": "Pluto‚ôá",
      "short_name": "Pl‚ôá",
      "house": 10,
      "house_name": "‚ôíÔłéAquarius",
      "longitude": 4.880895248744309,
      "longitude_dms": "4¬į 52‚Äô 51\""
    }
  ],
  "houses": {
    "0": [
      {
        "id": 10,
        "name": "Neptune‚ôÜ",
        "short_name": "Ne‚ôÜ",
        "house": 0,
        "house_name": "‚ôąAries",
        "longitude": 18.999035645060758,
        "longitude_dms": "18¬į 59‚Äô 57\""
      }
    ],
    "1": [],
    "2": [
      {
        "id": "L",
        "name": "Ascendant",
        "short_name": "Asc",
        "house": 2,
        "house_name": "‚ôäÔłéGemini",
        "longitude": 9.406798488562117,
        "longitude_dms": "9¬į 24‚Äô 24\""
      },
      {
        "id": 9,
        "name": "Uranus‚õĘ",
        "short_name": "Ur‚õĘ",
        "house": 2,
        "house_name": "‚ôäÔłéGemini",
        "longitude": 5.043360729221149,
        "longitude_dms": "5¬į 2‚Äô 36\""
      }
    ],
    "3": [
      {
        "id": 1,
        "name": "Moon‚ėĺ",
        "short_name": "Mo‚ėĺ",
        "house": 3,
        "house_name": "‚ôčÔłéCancer",
        "longitude": 1.3397530748991358,
        "longitude_dms": "1¬į 20‚Äô 23\""
      },
      {
        "id": 2,
        "name": "Mars‚ôā",
        "short_name": "Ma‚ôā",
        "house": 3,
        "house_name": "‚ôčÔłéCancer",
        "longitude": 18.424194198893474,
        "longitude_dms": "18¬į 25‚Äô 27\""
      },
      {
        "id": 3,
        "name": "Mercury‚ėŅ",
        "short_name": "Me‚ėŅ",
        "house": 3,
        "house_name": "‚ôčÔłéCancer",
        "longitude": 29.358620782087428,
        "longitude_dms": "29¬į 21‚Äô 31\""
      }
    ],
    "4": [],
    "5": [
      {
        "id": 0,
        "name": "Sun‚ėČ",
        "short_name": "Su‚ėČ",
        "house": 5,
        "house_name": "‚ôćÔłéVirgo",
        "longitude": 5.92230594716375,
        "longitude_dms": "5¬į 55‚Äô 20\""
      },
      {
        "id": 5,
        "name": "Venus‚ôÄ",
        "short_name": "Ve‚ôÄ",
        "house": 5,
        "house_name": "‚ôćÔłéVirgo",
        "longitude": 18.811939700024027,
        "longitude_dms": "18¬į 48‚Äô 43\""
      }
    ],
    "6": [],
    "7": [
      {
        "id": 6,
        "name": "Saturn‚ôĄ",
        "short_name": "Sa‚ôĄ",
        "house": 7,
        "house_name": "‚ôŹÔłéScorpio",
        "longitude": 4.603429656026037,
        "longitude_dms": "4¬į 36‚Äô 12\""
      }
    ],
    "8": [
      {
        "id": 4,
        "name": "Jupiter‚ôÉ",
        "short_name": "Ju‚ôÉ",
        "house": 8,
        "house_name": "‚ôźÔłéSagittarius",
        "longitude": 4.490410215297061,
        "longitude_dms": "4¬į 29‚Äô 25\""
      },
      {
        "id": 7,
        "name": "Raagu‚ėä",
        "short_name": "Ra‚ėä",
        "house": 8,
        "house_name": "‚ôźÔłéSagittarius",
        "longitude": 2.943214876112961,
        "longitude_dms": "2¬į 56‚Äô 36\""
      },
      {
        "id": 8,
        "name": "Kethu‚ėč",
        "short_name": "Ke‚ėč",
        "house": 8,
        "house_name": "‚ôźÔłéSagittarius",
        "longitude": 2.943214876112961,
        "longitude_dms": "2¬į 56‚Äô 36\""
      }
    ],
    "9": [],
    "10": [
      {
        "id": 11,
        "name": "Pluto‚ôá",
        "short_name": "Pl‚ôá",
        "house": 10,
        "house_name": "‚ôíÔłéAquarius",
        "longitude": 4.880895248744309,
        "longitude_dms": "4¬į 52‚Äô 51\""
      }
    ],
    "11": []
  },
  "ascendant": {
    "house": 2,
    "house_name": "‚ôäÔłéGemini",
    "longitude": 9.406798488562117,
    "longitude_dms": "9¬į 24‚Äô 24\""
  },
  "birth_data": {
    "name": "Prachi Gaur",
    "place": "saharanpur",
    "date": "1996-09-20",
    "time": "01:50:00"
  }
}