{
  "chart_type": "D1",
  "divisional_factor": 1,
  "chart_name": "Rasi Chart",
  "signification": "Birth Chart, Overall Life",
  "planets": [
    {
      "id": "L",
      "name": "Ascendant",
      "short_name": "Asc",
      "house": 3,
      "house_name": "‚ôčÔłéCancer",
      "longitude": 4.117675125683419,
      "longitude_dms": "4¬į 7‚Äô 4\""
    },
    {
      "id": 0,
      "name": "Sun‚ėČ",
      "short_name": "Su‚ėČ",
      "house": 8,
      "house_name": "‚ôźÔłéSagittarius",
      "longitude": 13.667437597070688,
      "longitude_dms": "13¬į 40‚Äô 3\""
    },
    {
      "id": 1,
      "name": "Moon‚ėĺ",
      "short_name": "Mo‚ėĺ",
      "house": 11,
      "house_name": "‚ôďÔłéPisces",
      "longitude": 10.75908445288411,
      "longitude_dms": "10¬į 45‚Äô 33\""
    },
    {
      "id": 2,
      "name": "Mars‚ôā",
      "short_name": "Ma‚ôā",
      "house": 8,
      "house_name": "‚ôźÔłéSagittarius",
      "longitude": 28.83031379176913,
      "longitude_dms": "28¬į 49‚Äô 49\""
    },
    {
      "id": 3,
      "name": "Mercury‚ėŅ",
      "short_name": "Me‚ėŅ",
      "house": 9,
      "house_name": "‚ôĎÔłéCapricorn",
      "longitude": 2.106782996621348,
      "longitude_dms": "2¬į 6‚Äô 24\""
    },
    {
      "id": 4,
      "name": "Jupiter‚ôÉ",
      "short_name": "Ju‚ôÉ",
      "house": 8,
      "house_name": "‚ôźÔłéSagittarius",
      "longitude": 6.036364571106446,
      "longitude_dms": "6¬į 2‚Äô 11\""
    },
    {
      "id": 5,
      "name": "Venus‚ôÄ",
      "short_name": "Ve‚ôÄ",
      "house": 9,
      "house_name": "‚ôĎÔłéCapricorn",
      "longitude": 15.721429466890015,
      "longitude_dms": "15¬į 43‚Äô 17\""
    },
    {
      "id": 6,
      "name": "Saturn‚ôĄ",
      "short_name": "Sa‚ôĄ",
      "house": 10,
      "house_name": "‚ôíÔłéAquarius",
      "longitude": 26.507548251601975,
      "longitude_dms": "26¬į 30‚Äô 27\""
    },
    {
      "id": 7,
      "name": "Raagu‚ėä",
      "short_name": "Ra‚ėä",
      "house": 6,
      "house_name": "‚ôéÔłéLibra",
      "longitude": 0.8472000085284606,
      "longitude_dms": "0¬į 50‚Äô 50\""
    },
    {
      "id": 8,
      "name": "Kethu‚ėč",
      "short_name": "Ke‚ėč",
      "house": 0,
      "house_name": "‚ôąAries",
      "longitude": 0.847200008528489,
      "longitude_dms": "0¬į 50‚Äô 50\""
    },
    {
      "id": 9,
      "name": "Uranus‚õĘ",
      "short_name": "Ur‚õĘ",
      "house": 9,
      "house_name": "‚ôĎÔłéCapricorn",
      "longitude": 6.4966064498980245,
      "longitude_dms": "6¬į 29‚Äô 48\""
    },
    {
      "id": 10,
      "name": "Neptune‚ôÜ",
      "short_name": "Ne‚ôÜ",
      "house": 9,
      "house_name": "‚ôĎÔłéCapricorn",
      "longitude": 1.8908183923416573,
      "longitude_dms": "1¬į 53‚Äô 27\""
    },
    {
      "id": 11,
      "name": "Pluto‚ôá",
      "short_name": "Pl‚ôá",
      "house": 7,
      "house_name": "‚ôŹÔłéScorpio",
      "longitude": 9.171622897167254,
      "longitude_dms": "9¬į 10‚Äô 18\""
    }
  ],
  "houses": {
    "0": [
      {
        "id": 8,
        "name": "Kethu‚ėč",
        "short_name": "Ke‚ėč",
        "house": 0,
        "house_name": "‚ôąAries",
        "longitude": 0.847200008528489,
        "longitude_dms": "0¬į 50‚Äô 50\""
      }
    ],
    "1": [],
    "2": [],
    "3": [
      {
        "id": "L",
        "name": "Ascendant",
        "short_name": "Asc",
        "house": 3,
        "house_name": "‚ôčÔłéCancer",
        "longitude": 4.117675125683419,
        "longitude_dms": "4¬į 7‚Äô 4\""
      }
    ],
    "4": [],
    "5": [],
    "6": [
      {
        "id": 7,
        "name": "Raagu‚ėä",
        "short_name": "Ra‚ėä",
        "house": 6,
        "house_name": "‚ôéÔłéLibra",
        "longitude": 0.8472000085284606,
        "longitude_dms": "0¬į 50‚Äô 50\""
      }
    ],
    "7": [
      {
        "id": 11,
        "name": "Pluto‚ôá",
        "short_name": "Pl‚ôá",
        "house": 7,
        "house_name": "‚ôŹÔłéScorpio",
        "longitude": 9.171622897167254,
        "longitude_dms": "9¬į 10‚Äô 18\""
      }
    ],
    "8": [
      {
        "id": 0,
        "name": "Sun‚ėČ",
        "short_name": "Su‚ėČ",
        "house": 8,
        "house_name": "‚ôźÔłéSagittarius",
        "longitude": 13.667437597070688,
        "longitude_dms": "13¬į 40‚Äô 3\""
      },
      {
        "id": 2,
        "name": "Mars‚ôā",
        "short_name": "Ma‚ôā",
        "house": 8,
        "house_name": "‚ôźÔłéSagittarius",
        "longitude": 28.83031379176913,
        "longitude_dms": "28¬į 49‚Äô 49\""
      },
      {
        "id": 4,
        "name": "Jupiter‚ôÉ",
        "short_name": "Ju‚ôÉ",
        "house": 8,
        "house_name": "‚ôźÔłéSagittarius",
        "longitude": 6.036364571106446,
        "longitude_dms": "6¬į 2‚Äô 11\""
      }
    ],
    "9": [
      {
        "id": 3,
        "name": "Mercury‚ėŅ",
        "short_name": "Me‚ėŅ",
        "house": 9,
        "house_name": "‚ôĎÔłéCapricorn",
        "longitude": 2.106782996621348,
        "longitude_dms": "2¬į 6‚Äô 24\""
      },
      {
        "id": 5,
        "name": "Venus‚ôÄ",
        "short_name": "Ve‚ôÄ",
        "house": 9,
        "house_name": "‚ôĎÔłéCapricorn",
        "longitude": 15.721429466890015,
        "longitude_dms": "15¬į 43‚Äô 17\""
      },
      {
        "id": 9,
        "name": "Uranus‚õĘ",
        "short_name": "Ur‚õĘ",
        "house": 9,
        "house_name": "‚ôĎÔłéCapricorn",
        "longitude": 6.4966064498980245,
        "longitude_dms": "6¬į 29‚Äô 48\""
      },
      {
        "id": 10,
        "name": "Neptune‚ôÜ",
        "short_name": "Ne‚ôÜ",
        "house": 9,
        "house_name": "‚ôĎÔłéCapricorn",
        "longitude": 1.8908183923416573,
        "longitude_dms": "1¬į 53‚Äô 27\""
      }
    ],
    "10": [
      {
        "id": 6,
        "name": "Saturn‚ôĄ",
        "short_name": "Sa‚ôĄ",
        "house": 10,
        "house_name": "‚ôíÔłéAquarius",
        "longitude": 26.507548251601975,
        "longitude_dms": "26¬į 30‚Äô 27\""
      }
    ],
    "11": [
      {
        "id": 1,
        "name": "Moon‚ėĺ",
        "short_name": "Mo‚ėĺ",
        "house": 11,
        "house_name": "‚ôďÔłéPisces",
        "longitude": 10.75908445288411,
        "longitude_dms": "10¬į 45‚Äô 33\""
      }
    ]
  },
  "ascendant": {
    "house": 3,
    "house_name": "‚ôčÔłéCancer",
    "longitude": 4.117675125683419,
    "longitude_dms": "4¬į 7‚Äô 4\""
  },
  "birth_data": {
    "name": "Jai Mishra",
    "place": "Allahabad",
    "date": "1995-12-28",
    "time": "18:50:00"
  }
}